c3toc/__init__.py
c3toc/api.py
c3toc/exceptions.py
c3toc/metadata.py
pyc3toc-1.0.0.dist-info/LICENSE
pyc3toc-1.0.0.dist-info/METADATA
pyc3toc-1.0.0.dist-info/WHEEL
pyc3toc-1.0.0.dist-info/top_level.txt
pyc3toc-1.0.0.dist-info/RECORD
